{"Packages":[{"Name":"workerpool/poolworker","Functions":[{"Name":"New","File":"/home/mbarry/projects/workerpool/poolworker/dispatcher.go","Start":357,"End":704,"Statements":[{"Start":405,"End":688,"Reached":2},{"Start":690,"End":702,"Reached":2}]},{"Name":"Dispatcher.Start","File":"/home/mbarry/projects/workerpool/poolworker/dispatcher.go","Start":706,"End":921,"Statements":[{"Start":750,"End":780,"Reached":1},{"Start":782,"End":892,"Reached":1},{"Start":821,"End":861,"Reached":2},{"Start":864,"End":889,"Reached":2},{"Start":894,"End":909,"Reached":1},{"Start":911,"End":919,"Reached":1}]},{"Name":"Dispatcher.Stop","File":"/home/mbarry/projects/workerpool/poolworker/dispatcher.go","Start":923,"End":1110,"Statements":[{"Start":954,"End":987,"Reached":1},{"Start":989,"End":1005,"Reached":1},{"Start":1007,"End":1021,"Reached":1},{"Start":1023,"End":1036,"Reached":1},{"Start":1038,"End":1050,"Reached":1},{"Start":1052,"End":1095,"Reached":1},{"Start":1084,"End":1092,"Reached":2},{"Start":1097,"End":1108,"Reached":1}]},{"Name":"Dispatcher.Queue","File":"/home/mbarry/projects/workerpool/poolworker/dispatcher.go","Start":1112,"End":1282,"Statements":[{"Start":1182,"End":1214,"Reached":1},{"Start":1199,"End":1211,"Reached":0},{"Start":1216,"End":1231,"Reached":1},{"Start":1233,"End":1267,"Reached":1},{"Start":1269,"End":1280,"Reached":1}]},{"Name":"Dispatcher.dispatch","File":"/home/mbarry/projects/workerpool/poolworker/dispatcher.go","Start":1284,"End":1535,"Statements":[{"Start":1319,"End":1355,"Reached":1},{"Start":1357,"End":1533,"Reached":1},{"Start":1365,"End":1530,"Reached":1},{"Start":1403,"End":1422,"Reached":0},{"Start":1426,"End":1441,"Reached":0},{"Start":1462,"End":1516,"Reached":1},{"Start":1488,"End":1511,"Reached":1},{"Start":1520,"End":1526,"Reached":1}]},{"Name":"@65:8","File":"/home/mbarry/projects/workerpool/poolworker/dispatcher.go","Start":1325,"End":1353,"Statements":[{"Start":1334,"End":1351,"Reached":1}]},{"Name":"Dispatcher.processWaitingTasks","File":"/home/mbarry/projects/workerpool/poolworker/dispatcher.go","Start":1537,"End":1732,"Statements":[{"Start":1583,"End":1627,"Reached":1},{"Start":1629,"End":1730,"Reached":1},{"Start":1637,"End":1660,"Reached":2},{"Start":1663,"End":1687,"Reached":2},{"Start":1677,"End":1683,"Reached":1},{"Start":1690,"End":1709,"Reached":1},{"Start":1712,"End":1727,"Reached":1}]},{"Name":"NewTask","File":"/home/mbarry/projects/workerpool/poolworker/worker.go","Start":194,"End":415,"Statements":[{"Start":297,"End":413,"Reached":1}]},{"Name":"NewWorker","File":"/home/mbarry/projects/workerpool/poolworker/worker.go","Start":522,"End":702,"Statements":[{"Start":601,"End":700,"Reached":2}]},{"Name":"Worker.Start","File":"/home/mbarry/projects/workerpool/poolworker/worker.go","Start":704,"End":1333,"Statements":[{"Start":750,"End":759,"Reached":2},{"Start":761,"End":1290,"Reached":2},{"Start":1292,"End":1331,"Reached":2}]},{"Name":"@43:5","File":"/home/mbarry/projects/workerpool/poolworker/worker.go","Start":764,"End":1288,"Statements":[{"Start":775,"End":790,"Reached":2},{"Start":793,"End":1285,"Reached":2},{"Start":802,"End":1281,"Reached":6},{"Start":877,"End":947,"Reached":3},{"Start":891,"End":929,"Reached":2},{"Start":935,"End":941,"Reached":2},{"Start":952,"End":988,"Reached":1},{"Start":974,"End":982,"Reached":0},{"Start":993,"End":1068,"Reached":1},{"Start":1073,"End":1105,"Reached":1},{"Start":1110,"End":1276,"Reached":1},{"Start":1131,"End":1199,"Reached":0},{"Start":1218,"End":1270,"Reached":1}]},{"Name":"Worker.Stop","File":"/home/mbarry/projects/workerpool/poolworker/worker.go","Start":1335,"End":1379,"Statements":[{"Start":1361,"End":1377,"Reached":2}]}]}]}
